unet_pytorch/__init__.py
unet_pytorch/data.py
unet_pytorch/model.py
unet_pytorch/predict.py
unet_pytorch/train.py
unet_pytorch/utils.py
unet_pytorch-0.4.3.dist-info/LICENSE
unet_pytorch-0.4.3.dist-info/METADATA
unet_pytorch-0.4.3.dist-info/WHEEL
unet_pytorch-0.4.3.dist-info/RECORD
