Metadata-Version: 2.1
Name: unet-pytorch
Version: 0.4.3
Summary: PyTorch implementation of a convolutional neural network (U-Net)
Home-page: https://github.com/giansimone/unet-pytorch
License: MIT
Author: Giansimone Perrino
Author-email: hello@giansimone.dev
Requires-Python: >=3.11,<4.0
Classifier: License :: OSI Approved :: MIT License
Classifier: Programming Language :: Python :: 3
Classifier: Programming Language :: Python :: 3.11
Classifier: Programming Language :: Python :: 3.12
Classifier: Programming Language :: Python :: 3.13
Requires-Dist: matplotlib (>=3.10.1,<4.0.0)
Requires-Dist: notebook (>=7.3.3,<8.0.0)
Requires-Dist: numpy (>=2.2.4,<3.0.0)
Requires-Dist: scikit-image (>=0.25.2,<0.26.0)
Requires-Dist: scikit-learn (>=1.6.1,<2.0.0)
Requires-Dist: torch (>=2.6.0,<3.0.0)
Requires-Dist: torchvision (>=0.21.0,<0.22.0)
Project-URL: Repository, https://github.com/giansimone/unet-pytorch
